molecular_columns/__init__.py
molecular_columns/_version.py
molecular_columns/c18o.dat
molecular_columns/col_c18o.py
molecular_columns/col_dcn.py
molecular_columns/col_dcop.py
molecular_columns/col_h13cop.py
molecular_columns/col_nh2d.py
molecular_columns/col_so.py
molecular_columns/common_functions.py
molecular_columns/dcn.csv
molecular_columns/dcn.dat
molecular_columns/test/__init__.py
molecular_columns/test/test_col_c18o.py
molecular_columns/test/test_col_dcn.py
molecular_columns/test/test_col_dcop.py
molecular_columns/test/test_col_h13cop.py
molecular_columns/test/test_col_nh2d.py
molecular_columns/test/test_col_so.py
molecular_columns/test/test_common_functions.py
molecular_columns-0.9.dev0.dist-info/licenses/LICENSE
molecular_columns-0.9.dev0.dist-info/METADATA
molecular_columns-0.9.dev0.dist-info/WHEEL
molecular_columns-0.9.dev0.dist-info/top_level.txt
molecular_columns-0.9.dev0.dist-info/RECORD
