Metadata-Version: 2.4
Name: molecular_columns
Version: 0.9.dev0
Summary: Column density calculations of molecular especies.
Author-email: "Jaime E. Pineda" <jpineda@mpe.mpg.de>
Maintainer-email: "Jaime E. Pineda" <jpineda@mpe.mpg.de>
License: MIT License
Project-URL: Homepage, https://github.com/jpinedaf/molecular_columns
Requires-Python: >=3.7
License-File: LICENSE
Requires-Dist: importlib-resources; python_version < "3.9"
Requires-Dist: astropy>=5.0
Requires-Dist: numpy
Requires-Dist: pytest
Requires-Dist: pytest-cov
Dynamic: license-file
